stardate/__init__.py
stardate-1.3.1.dist-info/METADATA
stardate-1.3.1.dist-info/RECORD
stardate-1.3.1.dist-info/WHEEL
stardate-1.3.1.dist-info/top_level.txt
