Metadata-Version: 2.1
Name: stardate
Version: 1.3.1
Summary: Represent points in time as fractional years in UTC
Home-page: UNKNOWN
Author: Chris Oei
Author-email: chris.oei@gmail.com
License: MIT
Platform: UNKNOWN
Classifier: Programming Language :: Python :: 3
Classifier: License :: OSI Approved :: MIT License
Classifier: Operating System :: OS Independent
Requires-Dist: python-dateutil
